{
    "Assembly": [],
    "Cycles": {
        "1": [
            {
                "Fetch stage": {
                    "Program counter": 0,
                    "Raw instruction": "0x01328233"
                }
            }
        ],
        "2": [
            {
                "Creating alias": {
                    "Architectural register": "tp",
                    "Physical register created": 32,
                    "Current mapping": {
                        "zero": 0,
                        "ra": 1,
                        "sp": 2,
                        "gp": 3,
                        "tp": 32,
                        "t0": 5,
                        "t1": 6,
                        "t2": 7,
                        "s0": 8,
                        "s1": 9,
                        "a0": 10,
                        "a1": 11,
                        "a2": 12,
                        "a3": 13,
                        "a4": 14,
                        "a5": 15,
                        "a6": 16,
                        "a7": 17,
                        "s2": 18,
                        "s3": 19,
                        "s4": 20,
                        "s5": 21,
                        "s6": 22,
                        "s7": 23,
                        "s8": 24,
                        "s9": 25,
                        "s10": 26,
                        "s11": 27,
                        "t3": 28,
                        "t4": 29,
                        "t5": 30,
                        "t6": 31
                    },
                    "Free registers": {
                        "Empty": false,
                        "Full": false,
                        "List": [
                            33,
                            34,
                            35,
                            36,
                            37,
                            38,
                            39,
                            40,
                            41,
                            42,
                            43,
                            44,
                            45,
                            46,
                            47,
                            48,
                            49,
                            50,
                            51,
                            52,
                            53,
                            54,
                            55,
                            56,
                            57,
                            58,
                            59,
                            60,
                            61,
                            62,
                            63
                        ]
                    }
                }
            },
            {
                "Decode stage": {
                    "To fetch": {
                        "Has a next pc": true,
                        "Next pc": 1
                    },
                    "To issue": {
                        "Has decoded an instruction": true,
                        "Program counter": 0,
                        "Func 3": 0,
                        "Is Func7 0b0000000": true,
                        "Is Func7 0b0000001": false,
                        "Is Func7 0b0100000": false,
                        "Packed immediate": 0,
                        "Use destination": true,
                        "Use source 1": true,
                        "Use source 2": true,
                        "Physical destination": 32,
                        "Physical source 1": 5,
                        "Physical source 2": 19,
                        "Invalid instruction": false
                    }
                }
            }
        ],
        "3": [
            {
                "Fetch stage": {
                    "Program counter": 1,
                    "Raw instruction": "0xfff4c013"
                }
            }
        ],
        "4": [
            {
                "Creating alias": {
                    "Architectural register": "zero",
                    "Physical register created": 33,
                    "Current mapping": {
                        "zero": 33,
                        "ra": 1,
                        "sp": 2,
                        "gp": 3,
                        "tp": 32,
                        "t0": 5,
                        "t1": 6,
                        "t2": 7,
                        "s0": 8,
                        "s1": 9,
                        "a0": 10,
                        "a1": 11,
                        "a2": 12,
                        "a3": 13,
                        "a4": 14,
                        "a5": 15,
                        "a6": 16,
                        "a7": 17,
                        "s2": 18,
                        "s3": 19,
                        "s4": 20,
                        "s5": 21,
                        "s6": 22,
                        "s7": 23,
                        "s8": 24,
                        "s9": 25,
                        "s10": 26,
                        "s11": 27,
                        "t3": 28,
                        "t4": 29,
                        "t5": 30,
                        "t6": 31
                    },
                    "Free registers": {
                        "Empty": false,
                        "Full": false,
                        "List": [
                            34,
                            35,
                            36,
                            37,
                            38,
                            39,
                            40,
                            41,
                            42,
                            43,
                            44,
                            45,
                            46,
                            47,
                            48,
                            49,
                            50,
                            51,
                            52,
                            53,
                            54,
                            55,
                            56,
                            57,
                            58,
                            59,
                            60,
                            61,
                            62,
                            63
                        ]
                    }
                }
            },
            {
                "Decode stage": {
                    "To fetch": {
                        "Has a next pc": true,
                        "Next pc": 2
                    },
                    "To issue": {
                        "Has decoded an instruction": true,
                        "Program counter": 1,
                        "Func 3": 4,
                        "Is Func7 0b0000000": false,
                        "Is Func7 0b0000001": false,
                        "Is Func7 0b0100000": false,
                        "Packed immediate": 4294967295,
                        "Use destination": true,
                        "Use source 1": true,
                        "Use source 2": false,
                        "Physical destination": 33,
                        "Physical source 1": 9,
                        "Physical source 2": 19,
                        "Invalid instruction": false
                    }
                }
            }
        ],
        "5": [
            {
                "Fetch stage": {
                    "Program counter": 2,
                    "Raw instruction": "0xfe242e23"
                }
            }
        ],
        "6": [
            {
                "Decode stage": {
                    "To fetch": {
                        "Has a next pc": true,
                        "Next pc": 3
                    },
                    "To issue": {
                        "Has decoded an instruction": true,
                        "Program counter": 2,
                        "Func 3": 2,
                        "Is Func7 0b0000000": false,
                        "Is Func7 0b0000001": false,
                        "Is Func7 0b0100000": false,
                        "Packed immediate": 4294967292,
                        "Use destination": false,
                        "Use source 1": true,
                        "Use source 2": true,
                        "Physical destination": 33,
                        "Physical source 1": 8,
                        "Physical source 2": 2,
                        "Invalid instruction": false
                    }
                }
            }
        ],
        "7": [
            {
                "Fetch stage": {
                    "Program counter": 3,
                    "Raw instruction": "0x00000fb7"
                }
            }
        ],
        "8": [
            {
                "Creating alias": {
                    "Architectural register": "t6",
                    "Physical register created": 34,
                    "Current mapping": {
                        "zero": 33,
                        "ra": 1,
                        "sp": 2,
                        "gp": 3,
                        "tp": 32,
                        "t0": 5,
                        "t1": 6,
                        "t2": 7,
                        "s0": 8,
                        "s1": 9,
                        "a0": 10,
                        "a1": 11,
                        "a2": 12,
                        "a3": 13,
                        "a4": 14,
                        "a5": 15,
                        "a6": 16,
                        "a7": 17,
                        "s2": 18,
                        "s3": 19,
                        "s4": 20,
                        "s5": 21,
                        "s6": 22,
                        "s7": 23,
                        "s8": 24,
                        "s9": 25,
                        "s10": 26,
                        "s11": 27,
                        "t3": 28,
                        "t4": 29,
                        "t5": 30,
                        "t6": 34
                    },
                    "Free registers": {
                        "Empty": false,
                        "Full": false,
                        "List": [
                            35,
                            36,
                            37,
                            38,
                            39,
                            40,
                            41,
                            42,
                            43,
                            44,
                            45,
                            46,
                            47,
                            48,
                            49,
                            50,
                            51,
                            52,
                            53,
                            54,
                            55,
                            56,
                            57,
                            58,
                            59,
                            60,
                            61,
                            62,
                            63
                        ]
                    }
                }
            },
            {
                "Decode stage": {
                    "To fetch": {
                        "Has a next pc": true,
                        "Next pc": 4
                    },
                    "To issue": {
                        "Has decoded an instruction": true,
                        "Program counter": 3,
                        "Func 3": 0,
                        "Is Func7 0b0000000": true,
                        "Is Func7 0b0000001": false,
                        "Is Func7 0b0100000": false,
                        "Packed immediate": 0,
                        "Use destination": true,
                        "Use source 1": false,
                        "Use source 2": false,
                        "Physical destination": 34,
                        "Physical source 1": 8,
                        "Physical source 2": 2,
                        "Invalid instruction": false
                    }
                }
            }
        ],
        "9": [
            {
                "Fetch stage": {
                    "Program counter": 4,
                    "Raw instruction": "0x00000000"
                }
            }
        ],
        "10": [
            {
                "Decode stage": {
                    "To fetch": {
                        "Has a next pc": true,
                        "Next pc": 5
                    },
                    "To issue": {
                        "Has decoded an instruction": true,
                        "Program counter": 4,
                        "Func 3": 0,
                        "Is Func7 0b0000000": true,
                        "Is Func7 0b0000001": false,
                        "Is Func7 0b0100000": false,
                        "Packed immediate": 0,
                        "Use destination": false,
                        "Use source 1": false,
                        "Use source 2": false,
                        "Physical destination": 34,
                        "Physical source 1": 8,
                        "Physical source 2": 2,
                        "Invalid instruction": true
                    }
                }
            }
        ],
        "11": [
            {
                "Fetch stage": {
                    "Program counter": 5,
                    "Raw instruction": "0x0140006f"
                }
            }
        ],
        "12": [
            {
                "Creating alias": {
                    "Architectural register": "zero",
                    "Physical register created": 35,
                    "Current mapping": {
                        "zero": 35,
                        "ra": 1,
                        "sp": 2,
                        "gp": 3,
                        "tp": 32,
                        "t0": 5,
                        "t1": 6,
                        "t2": 7,
                        "s0": 8,
                        "s1": 9,
                        "a0": 10,
                        "a1": 11,
                        "a2": 12,
                        "a3": 13,
                        "a4": 14,
                        "a5": 15,
                        "a6": 16,
                        "a7": 17,
                        "s2": 18,
                        "s3": 19,
                        "s4": 20,
                        "s5": 21,
                        "s6": 22,
                        "s7": 23,
                        "s8": 24,
                        "s9": 25,
                        "s10": 26,
                        "s11": 27,
                        "t3": 28,
                        "t4": 29,
                        "t5": 30,
                        "t6": 34
                    },
                    "Free registers": {
                        "Empty": false,
                        "Full": false,
                        "List": [
                            36,
                            37,
                            38,
                            39,
                            40,
                            41,
                            42,
                            43,
                            44,
                            45,
                            46,
                            47,
                            48,
                            49,
                            50,
                            51,
                            52,
                            53,
                            54,
                            55,
                            56,
                            57,
                            58,
                            59,
                            60,
                            61,
                            62,
                            63
                        ]
                    }
                }
            },
            {
                "Decode stage": {
                    "To fetch": {
                        "Has a next pc": true,
                        "Next pc": 10
                    },
                    "To issue": {
                        "Has decoded an instruction": true,
                        "Program counter": 5,
                        "Func 3": 0,
                        "Is Func7 0b0000000": true,
                        "Is Func7 0b0000001": false,
                        "Is Func7 0b0100000": false,
                        "Packed immediate": 0,
                        "Use destination": true,
                        "Use source 1": false,
                        "Use source 2": false,
                        "Physical destination": 35,
                        "Physical source 1": 8,
                        "Physical source 2": 2,
                        "Invalid instruction": false
                    }
                }
            }
        ],
        "13": [
            {
                "Fetch stage": {
                    "Program counter": 10,
                    "Raw instruction": "0x00000000"
                }
            }
        ],
        "14": [
            {
                "Decode stage": {
                    "To fetch": {
                        "Has a next pc": true,
                        "Next pc": 11
                    },
                    "To issue": {
                        "Has decoded an instruction": true,
                        "Program counter": 10,
                        "Func 3": 0,
                        "Is Func7 0b0000000": true,
                        "Is Func7 0b0000001": false,
                        "Is Func7 0b0100000": false,
                        "Packed immediate": 0,
                        "Use destination": false,
                        "Use source 1": false,
                        "Use source 2": false,
                        "Physical destination": 35,
                        "Physical source 1": 8,
                        "Physical source 2": 2,
                        "Invalid instruction": true
                    }
                }
            }
        ],
        "15": [
            {
                "Fetch stage": {
                    "Program counter": 11,
                    "Raw instruction": "0x00000000"
                }
            }
        ],
        "16": [
            {
                "Decode stage": {
                    "To fetch": {
                        "Has a next pc": true,
                        "Next pc": 12
                    },
                    "To issue": {
                        "Has decoded an instruction": true,
                        "Program counter": 11,
                        "Func 3": 0,
                        "Is Func7 0b0000000": true,
                        "Is Func7 0b0000001": false,
                        "Is Func7 0b0100000": false,
                        "Packed immediate": 0,
                        "Use destination": false,
                        "Use source 1": false,
                        "Use source 2": false,
                        "Physical destination": 35,
                        "Physical source 1": 8,
                        "Physical source 2": 2,
                        "Invalid instruction": true
                    }
                }
            }
        ],
        "17": [
            {
                "Fetch stage": {
                    "Program counter": 12,
                    "Raw instruction": "0x00000000"
                }
            }
        ],
        "18": [
            {
                "Decode stage": {
                    "To fetch": {
                        "Has a next pc": true,
                        "Next pc": 13
                    },
                    "To issue": {
                        "Has decoded an instruction": true,
                        "Program counter": 12,
                        "Func 3": 0,
                        "Is Func7 0b0000000": true,
                        "Is Func7 0b0000001": false,
                        "Is Func7 0b0100000": false,
                        "Packed immediate": 0,
                        "Use destination": false,
                        "Use source 1": false,
                        "Use source 2": false,
                        "Physical destination": 35,
                        "Physical source 1": 8,
                        "Physical source 2": 2,
                        "Invalid instruction": true
                    }
                }
            }
        ],
        "19": [
            {
                "Fetch stage": {
                    "Program counter": 13,
                    "Raw instruction": "0x00000000"
                }
            }
        ],
        "20": [
            {
                "Decode stage": {
                    "To fetch": {
                        "Has a next pc": true,
                        "Next pc": 14
                    },
                    "To issue": {
                        "Has decoded an instruction": true,
                        "Program counter": 13,
                        "Func 3": 0,
                        "Is Func7 0b0000000": true,
                        "Is Func7 0b0000001": false,
                        "Is Func7 0b0100000": false,
                        "Packed immediate": 0,
                        "Use destination": false,
                        "Use source 1": false,
                        "Use source 2": false,
                        "Physical destination": 35,
                        "Physical source 1": 8,
                        "Physical source 2": 2,
                        "Invalid instruction": true
                    }
                }
            }
        ],
        "21": [
            {
                "Fetch stage": {
                    "Program counter": 14,
                    "Raw instruction": "0x00000000"
                }
            }
        ],
        "22": [
            {
                "Decode stage": {
                    "To fetch": {
                        "Has a next pc": true,
                        "Next pc": 15
                    },
                    "To issue": {
                        "Has decoded an instruction": true,
                        "Program counter": 14,
                        "Func 3": 0,
                        "Is Func7 0b0000000": true,
                        "Is Func7 0b0000001": false,
                        "Is Func7 0b0100000": false,
                        "Packed immediate": 0,
                        "Use destination": false,
                        "Use source 1": false,
                        "Use source 2": false,
                        "Physical destination": 35,
                        "Physical source 1": 8,
                        "Physical source 2": 2,
                        "Invalid instruction": true
                    }
                }
            }
        ],
        "23": [
            {
                "Fetch stage": {
                    "Program counter": 15,
                    "Raw instruction": "0x00000000"
                }
            }
        ],
        "24": [
            {
                "Decode stage": {
                    "To fetch": {
                        "Has a next pc": true,
                        "Next pc": 16
                    },
                    "To issue": {
                        "Has decoded an instruction": true,
                        "Program counter": 15,
                        "Func 3": 0,
                        "Is Func7 0b0000000": true,
                        "Is Func7 0b0000001": false,
                        "Is Func7 0b0100000": false,
                        "Packed immediate": 0,
                        "Use destination": false,
                        "Use source 1": false,
                        "Use source 2": false,
                        "Physical destination": 35,
                        "Physical source 1": 8,
                        "Physical source 2": 2,
                        "Invalid instruction": true
                    }
                }
            }
        ],
        "25": [
            {
                "Fetch stage": {
                    "Program counter": 16,
                    "Raw instruction": "0x00000000"
                }
            }
        ],
        "26": [
            {
                "Decode stage": {
                    "To fetch": {
                        "Has a next pc": true,
                        "Next pc": 17
                    },
                    "To issue": {
                        "Has decoded an instruction": true,
                        "Program counter": 16,
                        "Func 3": 0,
                        "Is Func7 0b0000000": true,
                        "Is Func7 0b0000001": false,
                        "Is Func7 0b0100000": false,
                        "Packed immediate": 0,
                        "Use destination": false,
                        "Use source 1": false,
                        "Use source 2": false,
                        "Physical destination": 35,
                        "Physical source 1": 8,
                        "Physical source 2": 2,
                        "Invalid instruction": true
                    }
                }
            }
        ],
        "27": [
            {
                "Fetch stage": {
                    "Program counter": 17,
                    "Raw instruction": "0x00000000"
                }
            }
        ],
        "28": [
            {
                "Decode stage": {
                    "To fetch": {
                        "Has a next pc": true,
                        "Next pc": 18
                    },
                    "To issue": {
                        "Has decoded an instruction": true,
                        "Program counter": 17,
                        "Func 3": 0,
                        "Is Func7 0b0000000": true,
                        "Is Func7 0b0000001": false,
                        "Is Func7 0b0100000": false,
                        "Packed immediate": 0,
                        "Use destination": false,
                        "Use source 1": false,
                        "Use source 2": false,
                        "Physical destination": 35,
                        "Physical source 1": 8,
                        "Physical source 2": 2,
                        "Invalid instruction": true
                    }
                }
            }
        ],
        "29": [
            {
                "Fetch stage": {
                    "Program counter": 18,
                    "Raw instruction": "0x00000000"
                }
            }
        ],
        "30": [
            {
                "Decode stage": {
                    "To fetch": {
                        "Has a next pc": true,
                        "Next pc": 19
                    },
                    "To issue": {
                        "Has decoded an instruction": true,
                        "Program counter": 18,
                        "Func 3": 0,
                        "Is Func7 0b0000000": true,
                        "Is Func7 0b0000001": false,
                        "Is Func7 0b0100000": false,
                        "Packed immediate": 0,
                        "Use destination": false,
                        "Use source 1": false,
                        "Use source 2": false,
                        "Physical destination": 35,
                        "Physical source 1": 8,
                        "Physical source 2": 2,
                        "Invalid instruction": true
                    }
                }
            }
        ],
        "31": [
            {
                "Fetch stage": {
                    "Program counter": 19,
                    "Raw instruction": "0x00000000"
                }
            }
        ],
        "32": [
            {
                "Decode stage": {
                    "To fetch": {
                        "Has a next pc": true,
                        "Next pc": 20
                    },
                    "To issue": {
                        "Has decoded an instruction": true,
                        "Program counter": 19,
                        "Func 3": 0,
                        "Is Func7 0b0000000": true,
                        "Is Func7 0b0000001": false,
                        "Is Func7 0b0100000": false,
                        "Packed immediate": 0,
                        "Use destination": false,
                        "Use source 1": false,
                        "Use source 2": false,
                        "Physical destination": 35,
                        "Physical source 1": 8,
                        "Physical source 2": 2,
                        "Invalid instruction": true
                    }
                }
            }
        ],
        "33": [
            {
                "Fetch stage": {
                    "Program counter": 20,
                    "Raw instruction": "0x00000000"
                }
            }
        ],
        "34": [
            {
                "Decode stage": {
                    "To fetch": {
                        "Has a next pc": true,
                        "Next pc": 21
                    },
                    "To issue": {
                        "Has decoded an instruction": true,
                        "Program counter": 20,
                        "Func 3": 0,
                        "Is Func7 0b0000000": true,
                        "Is Func7 0b0000001": false,
                        "Is Func7 0b0100000": false,
                        "Packed immediate": 0,
                        "Use destination": false,
                        "Use source 1": false,
                        "Use source 2": false,
                        "Physical destination": 35,
                        "Physical source 1": 8,
                        "Physical source 2": 2,
                        "Invalid instruction": true
                    }
                }
            }
        ],
        "35": [
            {
                "Fetch stage": {
                    "Program counter": 21,
                    "Raw instruction": "0x00000000"
                }
            }
        ],
        "36": [
            {
                "Decode stage": {
                    "To fetch": {
                        "Has a next pc": true,
                        "Next pc": 22
                    },
                    "To issue": {
                        "Has decoded an instruction": true,
                        "Program counter": 21,
                        "Func 3": 0,
                        "Is Func7 0b0000000": true,
                        "Is Func7 0b0000001": false,
                        "Is Func7 0b0100000": false,
                        "Packed immediate": 0,
                        "Use destination": false,
                        "Use source 1": false,
                        "Use source 2": false,
                        "Physical destination": 35,
                        "Physical source 1": 8,
                        "Physical source 2": 2,
                        "Invalid instruction": true
                    }
                }
            }
        ],
        "37": [
            {
                "Fetch stage": {
                    "Program counter": 22,
                    "Raw instruction": "0x00000000"
                }
            }
        ],
        "38": [
            {
                "Decode stage": {
                    "To fetch": {
                        "Has a next pc": true,
                        "Next pc": 23
                    },
                    "To issue": {
                        "Has decoded an instruction": true,
                        "Program counter": 22,
                        "Func 3": 0,
                        "Is Func7 0b0000000": true,
                        "Is Func7 0b0000001": false,
                        "Is Func7 0b0100000": false,
                        "Packed immediate": 0,
                        "Use destination": false,
                        "Use source 1": false,
                        "Use source 2": false,
                        "Physical destination": 35,
                        "Physical source 1": 8,
                        "Physical source 2": 2,
                        "Invalid instruction": true
                    }
                }
            }
        ],
        "39": [
            {
                "Fetch stage": {
                    "Program counter": 23,
                    "Raw instruction": "0x00000000"
                }
            }
        ],
        "40": [
            {
                "Decode stage": {
                    "To fetch": {
                        "Has a next pc": true,
                        "Next pc": 24
                    },
                    "To issue": {
                        "Has decoded an instruction": true,
                        "Program counter": 23,
                        "Func 3": 0,
                        "Is Func7 0b0000000": true,
                        "Is Func7 0b0000001": false,
                        "Is Func7 0b0100000": false,
                        "Packed immediate": 0,
                        "Use destination": false,
                        "Use source 1": false,
                        "Use source 2": false,
                        "Physical destination": 35,
                        "Physical source 1": 8,
                        "Physical source 2": 2,
                        "Invalid instruction": true
                    }
                }
            }
        ],
        "41": [
            {
                "Fetch stage": {
                    "Program counter": 24,
                    "Raw instruction": "0x00000000"
                }
            }
        ],
        "42": [
            {
                "Decode stage": {
                    "To fetch": {
                        "Has a next pc": true,
                        "Next pc": 25
                    },
                    "To issue": {
                        "Has decoded an instruction": true,
                        "Program counter": 24,
                        "Func 3": 0,
                        "Is Func7 0b0000000": true,
                        "Is Func7 0b0000001": false,
                        "Is Func7 0b0100000": false,
                        "Packed immediate": 0,
                        "Use destination": false,
                        "Use source 1": false,
                        "Use source 2": false,
                        "Physical destination": 35,
                        "Physical source 1": 8,
                        "Physical source 2": 2,
                        "Invalid instruction": true
                    }
                }
            }
        ],
        "43": [
            {
                "Fetch stage": {
                    "Program counter": 25,
                    "Raw instruction": "0x00000000"
                }
            }
        ],
        "44": [
            {
                "Decode stage": {
                    "To fetch": {
                        "Has a next pc": true,
                        "Next pc": 26
                    },
                    "To issue": {
                        "Has decoded an instruction": true,
                        "Program counter": 25,
                        "Func 3": 0,
                        "Is Func7 0b0000000": true,
                        "Is Func7 0b0000001": false,
                        "Is Func7 0b0100000": false,
                        "Packed immediate": 0,
                        "Use destination": false,
                        "Use source 1": false,
                        "Use source 2": false,
                        "Physical destination": 35,
                        "Physical source 1": 8,
                        "Physical source 2": 2,
                        "Invalid instruction": true
                    }
                }
            }
        ],
        "45": [
            {
                "Fetch stage": {
                    "Program counter": 26,
                    "Raw instruction": "0x00000000"
                }
            }
        ],
        "46": [
            {
                "Decode stage": {
                    "To fetch": {
                        "Has a next pc": true,
                        "Next pc": 27
                    },
                    "To issue": {
                        "Has decoded an instruction": true,
                        "Program counter": 26,
                        "Func 3": 0,
                        "Is Func7 0b0000000": true,
                        "Is Func7 0b0000001": false,
                        "Is Func7 0b0100000": false,
                        "Packed immediate": 0,
                        "Use destination": false,
                        "Use source 1": false,
                        "Use source 2": false,
                        "Physical destination": 35,
                        "Physical source 1": 8,
                        "Physical source 2": 2,
                        "Invalid instruction": true
                    }
                }
            }
        ],
        "47": [
            {
                "Fetch stage": {
                    "Program counter": 27,
                    "Raw instruction": "0x00000000"
                }
            }
        ],
        "48": [
            {
                "Decode stage": {
                    "To fetch": {
                        "Has a next pc": true,
                        "Next pc": 28
                    },
                    "To issue": {
                        "Has decoded an instruction": true,
                        "Program counter": 27,
                        "Func 3": 0,
                        "Is Func7 0b0000000": true,
                        "Is Func7 0b0000001": false,
                        "Is Func7 0b0100000": false,
                        "Packed immediate": 0,
                        "Use destination": false,
                        "Use source 1": false,
                        "Use source 2": false,
                        "Physical destination": 35,
                        "Physical source 1": 8,
                        "Physical source 2": 2,
                        "Invalid instruction": true
                    }
                }
            }
        ],
        "49": [
            {
                "Fetch stage": {
                    "Program counter": 28,
                    "Raw instruction": "0x00000000"
                }
            }
        ],
        "50": [
            {
                "Decode stage": {
                    "To fetch": {
                        "Has a next pc": true,
                        "Next pc": 29
                    },
                    "To issue": {
                        "Has decoded an instruction": true,
                        "Program counter": 28,
                        "Func 3": 0,
                        "Is Func7 0b0000000": true,
                        "Is Func7 0b0000001": false,
                        "Is Func7 0b0100000": false,
                        "Packed immediate": 0,
                        "Use destination": false,
                        "Use source 1": false,
                        "Use source 2": false,
                        "Physical destination": 35,
                        "Physical source 1": 8,
                        "Physical source 2": 2,
                        "Invalid instruction": true
                    }
                }
            }
        ],
        "51": [
            {
                "Fetch stage": {
                    "Program counter": 29,
                    "Raw instruction": "0x00000000"
                }
            }
        ],
        "52": [
            {
                "Decode stage": {
                    "To fetch": {
                        "Has a next pc": true,
                        "Next pc": 30
                    },
                    "To issue": {
                        "Has decoded an instruction": true,
                        "Program counter": 29,
                        "Func 3": 0,
                        "Is Func7 0b0000000": true,
                        "Is Func7 0b0000001": false,
                        "Is Func7 0b0100000": false,
                        "Packed immediate": 0,
                        "Use destination": false,
                        "Use source 1": false,
                        "Use source 2": false,
                        "Physical destination": 35,
                        "Physical source 1": 8,
                        "Physical source 2": 2,
                        "Invalid instruction": true
                    }
                }
            }
        ],
        "53": [
            {
                "Fetch stage": {
                    "Program counter": 30,
                    "Raw instruction": "0x00000000"
                }
            }
        ],
        "54": [
            {
                "Decode stage": {
                    "To fetch": {
                        "Has a next pc": true,
                        "Next pc": 31
                    },
                    "To issue": {
                        "Has decoded an instruction": true,
                        "Program counter": 30,
                        "Func 3": 0,
                        "Is Func7 0b0000000": true,
                        "Is Func7 0b0000001": false,
                        "Is Func7 0b0100000": false,
                        "Packed immediate": 0,
                        "Use destination": false,
                        "Use source 1": false,
                        "Use source 2": false,
                        "Physical destination": 35,
                        "Physical source 1": 8,
                        "Physical source 2": 2,
                        "Invalid instruction": true
                    }
                }
            }
        ],
        "55": [
            {
                "Fetch stage": {
                    "Program counter": 31,
                    "Raw instruction": "0x00000000"
                }
            }
        ],
        "56": [
            {
                "Decode stage": {
                    "To fetch": {
                        "Has a next pc": true,
                        "Next pc": 32
                    },
                    "To issue": {
                        "Has decoded an instruction": true,
                        "Program counter": 31,
                        "Func 3": 0,
                        "Is Func7 0b0000000": true,
                        "Is Func7 0b0000001": false,
                        "Is Func7 0b0100000": false,
                        "Packed immediate": 0,
                        "Use destination": false,
                        "Use source 1": false,
                        "Use source 2": false,
                        "Physical destination": 35,
                        "Physical source 1": 8,
                        "Physical source 2": 2,
                        "Invalid instruction": true
                    }
                }
            }
        ],
        "57": [
            {
                "Fetch stage": {
                    "Program counter": 32,
                    "Raw instruction": "0x00000000"
                }
            }
        ]
    }
}